Metadata-Version: 2.1
Name: portfolio-backtester
Version: 0.1.0
Summary: universal portfolio backtester
Home-page: UNKNOWN
Author: zhudechuan
Author-email: zhudechuan.zzjj@hotmail.com
License: MIT
Keywords: portfolio,backtest
Platform: UNKNOWN
Classifier: Programming Language :: Python
Classifier: Programming Language :: Python :: 3.8
Classifier: Programming Language :: Python :: 3.9
Classifier: Operating System :: OS Independent
License-File: LICENSE.txt
Requires-Dist: numpy
Requires-Dist: pandas
Requires-Dist: scipy
Requires-Dist: scikit-learn
